Workbook

Sheet Baseline Forecast 
A1: ROE | B1: =21.41/100 -> 0.2141 | C1: Inputs to be estimated | F1: Baseline Forecast | O1: Note : Walmart's latest full-year financials are for fiscal year ending Jan 31, 2025
A2: Div rate | B2: =34.4/100 -> 0.344
A3: ke | B3: =6.12/100 -> 0.0612
A4: growth rate (g) | B4: needed if you use Terminal Value
O5: Assumptions for Key Inputs
C6: Forecast for 7 Years | O6: Base Year (Latest Financials) | P6: Fiscal Year Ending 31st Jan 2025
C7: Fiscal Year Ending 31st Jan 2026 | D7: Fiscal Year Ending 31st Jan 2027 | E7: Fiscal Year Ending 31st Jan 2028 | F7: Fiscal Year Ending 31st Jan 2029 | G7: Fiscal Year Ending 31st Jan 2030 | H7: Fiscal Year Ending 31st Jan 2031 | I7: Fiscal Year Ending 31st Jan 2032 | J7: TV if assumed | O7: Beginning Book Value as on 31st Jan 2025 (In Millions) | P7: 97421
A8: Beg BV (In Millions) | C8: 97421 | D8: =C11 -> 111103.74 | E8: =D11 -> 126708.22 | F8: =E11 -> 144504.33 | G8: =F11 -> 164799.91 | H8: =G11 -> 187945.99 | I8: =H11 -> 214342.93 | O8: Forecast Years starts From | P8: Fiscal Year Ending 31st Jan 2026
A9: NI | C9: =$B$1*C8 -> 20857.836 | D9: =$B$1*D8 -> 23787.311 | E9: =$B$1*E8 -> 27128.229 | F9: =$B$1*F8 -> 30938.378 | G9: =$B$1*G8 -> 35283.661 | H9: =$B$1*H8 -> 40239.237 | I9: =$B$1*I8 -> 45890.822 | O9: Shares of Common Stock Outstanding as of March 12, 2025 | P9: 8016849444
A10: -Div | C10: =$B$2*C9 -> 7175.0956 | D10: =$B$2*D9 -> 8182.8349 | E10: =$B$2*E9 -> 9332.1108 | F10: =$B$2*F9 -> 10642.802 | G10: =$B$2*G9 -> 12137.579 | H10: =$B$2*H9 -> 13842.298 | I10: =$B$2*I9 -> 15786.443 | O10: Shares of Common Stock Outstanding as of March 12, 2025 (In Millions) | P10: =P9/1000000 -> 8016.8494
A11: End BV | C11: =C8+C9-C10 -> 111103.74 | D11: =D8+D9-D10 -> 126708.22 | E11: =E8+E9-E10 -> 144504.33 | F11: =F8+F9-F10 -> 164799.91 | G11: =G8+G9-G10 -> 187945.99 | H11: =H8+H9-H10 -> 214342.93 | I11: =I8+I9-I10 -> 244447.31
A13: Actual Earnings (NI) | C13: =$B$1*C8 -> 20857.836 | D13: =$B$1*D8 -> 23787.311 | E13: =$B$1*E8 -> 27128.229 | F13: =$B$1*F8 -> 30938.378 | G13: =$B$1*G8 -> 35283.661 | H13: =$B$1*H8 -> 40239.237 | I13: =$B$1*I8 -> 45890.822
A14: Expected Earnings (re * BVE) | C14: =$B$3*C8 -> 5962.1652 | D14: =$B$3*D8 -> 6799.5489 | E14: =$B$3*E8 -> 7754.5428 | F14: =$B$3*F8 -> 8843.6653 | G14: =$B$3*G8 -> 10085.755 | H14: =$B$3*H8 -> 11502.295 | I14: =$B$3*I8 -> 13117.787
A15: Abnormal Earnings | C15: =C13-C14 -> 14895.671 | D15: =D13-D14 -> 16987.762 | E15: =E13-E14 -> 19373.686 | F15: =F13-F14 -> 22094.713 | G15: =G13-G14 -> 25197.906 | H15: =H13-H14 -> 28736.942 | I15: =I13-I14 -> 32773.034 | J15: 0
A16: Discount factor | C16: =1/(1+$B$3)^1 -> 0.94232944 | D16: =1/(1+$B$3)^2 -> 0.88798477 | E16: =1/(1+$B$3)^3 -> 0.83677419 | F16: =1/(1+$B$3)^4 -> 0.78851695 | G16: =1/(1+$B$3)^5 -> 0.74304274 | H16: =1/(1+$B$3)^6 -> 0.70019105 | I16: =1/(1+$B$3)^7 -> 0.65981063 | J16: =1/(1+$B$3)^7 -> 0.65981063
A17: PV | C17: =C15*C16 -> 14036.629 | D17: =D15*D16 -> 15084.874 | E17: =E15*E16 -> 16211.401 | F17: =F15*F16 -> 17422.056 | G17: =G15*G16 -> 18723.121 | H17: =H15*H16 -> 20121.35 | I17: =I15*I16 -> 21623.997 | J17: =J15*J16 -> 0
A18: SUM of PV | B18: =SUM(C17:I17) -> 123223.43
A19: Beg BV | B19: =C8 -> 97421
A20: PV of TV | B20: =J17 -> 0
A21: Firm Value | B21: =SUM(B18:B20) -> 220644.43
A22: Value per Share | B22: =B21/8016.85 -> 27.522584 | C22: (8,016,849,444 number of shares outstanding used)
A23: in 2025 (As Fiscal Year Ended on 31st Jan 2025 for 2024)
A25: Current Stock Price: (As of April 29, 2025) | B25: 95.7
A27: Projection | B27: Overvalued | C27: Current stock price is greater than the Value per share

Sheet Sensitivity Analysis 1
A1: ROE | B1: ='Baseline Forecast '!B1 -> 0.2141 | C1: Inputs to be estimated | F1: Sensitivity Analysis: Longer Horizon
A2: Div rate | B2: ='Baseline Forecast '!B2 -> 0.344
A3: ke | B3: ='Baseline Forecast '!B3 -> 0.0612
A4: growth rate (g) | B4: needed if you use Terminal Value
C6: Forecast for 11 Years
C7: ='Baseline Forecast '!C7 -> Fiscal Year Ending 31st Jan 2026 | D7: ='Baseline Forecast '!D7 -> Fiscal Year Ending 31st Jan 2027 | E7: ='Baseline Forecast '!E7 -> Fiscal Year Ending 31st Jan 2028 | F7: ='Baseline Forecast '!F7 -> Fiscal Year Ending 31st Jan 2029 | G7: ='Baseline Forecast '!G7 -> Fiscal Year Ending 31st Jan 2030 | H7: ='Baseline Forecast '!H7 -> Fiscal Year Ending 31st Jan 2031 | I7: ='Baseline Forecast '!I7 -> Fiscal Year Ending 31st Jan 2032 | J7: Fiscal Year Ending 31st Jan 2033 | K7: Fiscal Year Ending 31st Jan 2033 | L7: Fiscal Year Ending 31st Jan 2033 | M7: Fiscal Year Ending 31st Jan 2033 | N7: TV if assumed
A8: Beg BV | C8: ='Baseline Forecast '!C8 -> 97421 | D8: =C11 -> 111103.74 | E8: =D11 -> 126708.22 | F8: =E11 -> 144504.33 | G8: =F11 -> 164799.91 | H8: =G11 -> 187945.99 | I8: =H11 -> 214342.93 | J8: =I11 -> 244447.31 | K8: =J11 -> 278779.84 | ... M8: =L11 -> 362588.11
A9: NI | C9: =$B$1*C8 -> 20857.836 | D9: =$B$1*D8 -> 23787.311 | E9: =$B$1*E8 -> 27128.229 | F9: =$B$1*F8 -> 30938.378 | G9: =$B$1*G8 -> 35283.661 | H9: =$B$1*H8 -> 40239.237 | I9: =$B$1*I8 -> 45890.822 | J9: =$B$1*J8 -> 52336.169 | ... M9: =$B$1*M8 -> 77630.114
A10: -Div | C10: =$B$2*C9 -> 7175.0956 | D10: =$B$2*D9 -> 8182.8349 | E10: =$B$2*E9 -> 9332.1108 | F10: =$B$2*F9 -> 10642.802 | G10: =$B$2*G9 -> 12137.579 | H10: =$B$2*H9 -> 13842.298 | I10: =$B$2*I9 -> 15786.443 | J10: =$B$2*J9 -> 18003.642 | ... M10: =$B$2*M9 -> 26704.759
A11: End BV | C11: =C8+C9-C10 -> 111103.74 | D11: =D8+D9-D10 -> 126708.22 | E11: =E8+E9-E10 -> 144504.33 | F11: =F8+F9-F10 -> 164799.91 | G11: =G8+G9-G10 -> 187945.99 | H11: =H8+H9-H10 -> 214342.93 | I11: =I8+I9-I10 -> 244447.31 | J11: =J8+J9-J10 -> 278779.84 | ... M11: =M8+M9-M10 -> 413513.46
A13: Actual Earnings (NI) | C13: =$B$1*C8 -> 20857.836 | D13: =$B$1*D8 -> 23787.311 | E13: =$B$1*E8 -> 27128.229 | F13: =$B$1*F8 -> 30938.378 | G13: =$B$1*G8 -> 35283.661 | H13: =$B$1*H8 -> 40239.237 | I13: =$B$1*I8 -> 45890.822 | J13: =$B$1*J8 -> 52336.169 | ... M13: =$B$1*M8 -> 77630.114
A14: Expected Earnings (re * BVE) | C14: =$B$3*C8 -> 5962.1652 | D14: =$B$3*D8 -> 6799.5489 | E14: =$B$3*E8 -> 7754.5428 | F14: =$B$3*F8 -> 8843.6653 | G14: =$B$3*G8 -> 10085.755 | H14: =$B$3*H8 -> 11502.295 | I14: =$B$3*I8 -> 13117.787 | J14: =$B$3*J8 -> 14960.175 | ... M14: =$B$3*M8 -> 22190.392
A15: Abnormal Earnings | C15: =C13-C14 -> 14895.671 | D15: =D13-D14 -> 16987.762 | E15: =E13-E14 -> 19373.686 | F15: =F13-F14 -> 22094.713 | G15: =G13-G14 -> 25197.906 | H15: =H13-H14 -> 28736.942 | I15: =I13-I14 -> 32773.034 | J15: =J13-J14 -> 37375.994 | ... M15: =M13-M14 -> 55439.722 | N15: 0 | O15: Formula: last Abnormal Earnings*(1+g)/(ke-g)
A16: Discount factor | C16: =1/(1+$B$3)^1 -> 0.94232944 | D16: =1/(1+$B$3)^2 -> 0.88798477 | E16: =1/(1+$B$3)^3 -> 0.83677419 | F16: =1/(1+$B$3)^4 -> 0.78851695 | G16: =1/(1+$B$3)^5 -> 0.74304274 | H16: =1/(1+$B$3)^6 -> 0.70019105 | I16: =1/(1+$B$3)^7 -> 0.65981063 | J16: =1/(1+$B$3)^8 -> 0.62175898 | K16: =1/(1+$B$3)^9 -> 0.58590179 | L16: =1/(1+$B$3)^10 -> 0.55211251 | M16: =1/(1+$B$3)^11 -> 0.52027187 | N16: =1/(1+$B$3)^11 -> 0.52027187
A17: PV | C17: =C15*C16 -> 14036.629 | D17: =D15*D16 -> 15084.874 | E17: =E15*E16 -> 16211.401 | F17: =F15*F16 -> 17422.056 | G17: =G15*G16 -> 18723.121 | H17: =H15*H16 -> 20121.35 | I17: =I15*I16 -> 21623.997 | J17: =J15*J16 -> 23238.86 | ... N17: =N15*N16 -> 0
A18: SUM of PV | B18: =SUM(C17:M17) -> 227119.72
A19: Beg BV | B19: =C8 -> 97421
A20: PV of TV | B20: =N17 -> 0
A21: Firm Value | B21: =SUM(B18:B20) -> 324540.72
A22: Value per Share | B22: =B21/8016.85 -> 40.482324 | C22: ='Baseline Forecast '!C22 -> (8,016,849,444 number of shares outstanding used)
A23: ='Baseline Forecast '!A23 -> in 2025 (As Fiscal Year Ended on 31st Jan 2025 for 2024)
A25: Current Stock Price: (As of April 29, 2025) | B25: 95.7
A27: Projection | B27: Overvalued | C27: Current stock price is greater than the Value per share

Sheet Sensitivity Analysis 2
A1: ROE | B1: ='Baseline Forecast '!B1 -> 0.2141 | C1: Inputs to be estimated | F1: Sensitivity Analysis: Adding Terminal Value
A2: Div rate | B2: ='Baseline Forecast '!B2 -> 0.344
A3: ke | B3: ='Baseline Forecast '!B3 -> 0.0612
A4: growth rate (g) | B4: 0.03 | C4: I believe Walmart will grow slightly faster than inflation as the Industry is growing
C6: Forecast for 7 Years
C7: Fiscal Year Ending 31st Jan 2026 | D7: Fiscal Year Ending 31st Jan 2027 | E7: Fiscal Year Ending 31st Jan 2028 | F7: Fiscal Year Ending 31st Jan 2029 | G7: Fiscal Year Ending 31st Jan 2030 | H7: Fiscal Year Ending 31st Jan 2031 | I7: Fiscal Year Ending 31st Jan 2032 | J7: TV if assumed
A8: Beg BV | C8: ='Baseline Forecast '!C8 -> 97421 | D8: =C11 -> 111103.74 | E8: =D11 -> 126708.22 | F8: =E11 -> 144504.33 | G8: =F11 -> 164799.91 | H8: =G11 -> 187945.99 | I8: =H11 -> 214342.93
A9: NI | C9: =$B$1*C8 -> 20857.836 | D9: =$B$1*D8 -> 23787.311 | E9: =$B$1*E8 -> 27128.229 | F9: =$B$1*F8 -> 30938.378 | G9: =$B$1*G8 -> 35283.661 | H9: =$B$1*H8 -> 40239.237 | I9: =$B$1*I8 -> 45890.822
A10: -Div | C10: =$B$2*C9 -> 7175.0956 | D10: =$B$2*D9 -> 8182.8349 | E10: =$B$2*E9 -> 9332.1108 | F10: =$B$2*F9 -> 10642.802 | G10: =$B$2*G9 -> 12137.579 | H10: =$B$2*H9 -> 13842.298 | I10: =$B$2*I9 -> 15786.443
A11: End BV | C11: =C8+C9-C10 -> 111103.74 | D11: =D8+D9-D10 -> 126708.22 | E11: =E8+E9-E10 -> 144504.33 | F11: =F8+F9-F10 -> 164799.91 | G11: =G8+G9-G10 -> 187945.99 | H11: =H8+H9-H10 -> 214342.93 | I11: =I8+I9-I10 -> 244447.31
A13: Actual Earnings (NI) | C13: =$B$1*C8 -> 20857.836 | D13: =$B$1*D8 -> 23787.311 | E13: =$B$1*E8 -> 27128.229 | F13: =$B$1*F8 -> 30938.378 | G13: =$B$1*G8 -> 35283.661 | H13: =$B$1*H8 -> 40239.237 | I13: =$B$1*I8 -> 45890.822
A14: Expected Earnings (re * BVE) | C14: =$B$3*C8 -> 5962.1652 | D14: =$B$3*D8 -> 6799.5489 | E14: =$B$3*E8 -> 7754.5428 | F14: =$B$3*F8 -> 8843.6653 | G14: =$B$3*G8 -> 10085.755 | H14: =$B$3*H8 -> 11502.295 | I14: =$B$3*I8 -> 13117.787
A15: Abnormal Earnings | C15: =C13-C14 -> 14895.671 | D15: =D13-D14 -> 16987.762 | E15: =E13-E14 -> 19373.686 | F15: =F13-F14 -> 22094.713 | G15: =G13-G14 -> 25197.906 | H15: =H13-H14 -> 28736.942 | I15: =I13-I14 -> 32773.034 | J15: =I15*(1+$B$4)/($B$3-$B$4) -> 1081930.3 | K15: Formula: last Abnormal Earnings*(1+g)/(ke-g)
A16: Discount factor | C16: =1/(1+$B$3)^1 -> 0.94232944 | D16: =1/(1+$B$3)^2 -> 0.88798477 | E16: =1/(1+$B$3)^3 -> 0.83677419 | F16: =1/(1+$B$3)^4 -> 0.78851695 | G16: =1/(1+$B$3)^5 -> 0.74304274 | H16: =1/(1+$B$3)^6 -> 0.70019105 | I16: =1/(1+$B$3)^7 -> 0.65981063 | J16: =1/(1+$B$3)^7 -> 0.65981063
A17: PV | C17: =C15*C16 -> 14036.629 | D17: =D15*D16 -> 15084.874 | E17: =E15*E16 -> 16211.401 | F17: =F15*F16 -> 17422.056 | G17: =G15*G16 -> 18723.121 | H17: =H15*H16 -> 20121.35 | I17: =I15*I16 -> 21623.997 | J17: =J15*J16 -> 713869.12
A18: SUM of PV | B18: =SUM(C17:I17) -> 123223.43
A19: Beg BV | B19: =C8 -> 97421
A20: PV of TV | B20: =J17 -> 713869.12
A21: Firm Value | B21: =SUM(B18:B20) -> 934513.54
A22: Value per Share | B22: =B21/8016.85 -> 116.56867 | C22: (8,016,849,444 number of shares outstanding used)
A23: in 2025 (As Fiscal Year Ended on 31st Jan 2025 for 2024)
A25: Current Stock Price: (As of April 29, 2025) | B25: 95.7 | C25: Value per share is greater than the current stock price
